embroidepy/ZoomerPanelDemo.py
embroidepy/__init__.py
embroidepy/about.py
embroidepy/assets.py
embroidepy/embroideryview.py
embroidepy/main.py
embroidepy/simulatorview.py
embroidepy/statisticsview.py
embroidepy/stitcheditor.py
embroidepy/zmatrix.py
embroidepy/zoomerpanel.py
embroidepy-0.0.6.dist-info/LICENSE
embroidepy-0.0.6.dist-info/METADATA
embroidepy-0.0.6.dist-info/WHEEL
embroidepy-0.0.6.dist-info/entry_points.txt
embroidepy-0.0.6.dist-info/top_level.txt
embroidepy-0.0.6.dist-info/zip-safe
embroidepy-0.0.6.dist-info/RECORD
